pyswipe/__init__.py
pyswipe/constants.py
pyswipe/mlat_scalargrid.txt
pyswipe/mlt_scalargrid.txt
pyswipe/mlt_utils.py
pyswipe/model_utils.py
pyswipe/model_vector_to_txt.py
pyswipe/plot_utils.py
pyswipe/potential.txt
pyswipe/sh_utils.py
pyswipe/swipe.py
pyswipe/coefficients/SW_OPER_EIO_SHA_2E_00000000T000000_99999999T999999_0101.txt
pyswipe/tests/01__plot_cpcp_vs_hemi_bt_and_clockangle.py
pyswipe/tests/02__E_at_lowlatboundary.py
pyswipe/tests/03__hi-c_cpcp_vs_other_studies.py
pyswipe/tests/04__potential_dial_plots.py
pyswipe/tests/04__potential_dial_plots__alternative_levels.py
pyswipe/tests/05__emwork_dial_plots.py
pyswipe/tests/05__emwork_dial_plots__alternative_levels.py
pyswipe/tests/06__plot_emwork_vs_hemi_bt_and_clockangle.py
pyswipe/tests/08__conductance_dial_plots__filledcell.py
pyswipe/tests/09__dask_functions_for_large_input.py
pyswipe-0.9.8.1.dist-info/licenses/LICENSE
pyswipe-0.9.8.1.dist-info/METADATA
pyswipe-0.9.8.1.dist-info/WHEEL
pyswipe-0.9.8.1.dist-info/top_level.txt
pyswipe-0.9.8.1.dist-info/RECORD
