Metadata-Version: 2.4
Name: pyswipe
Version: 0.9.8.1
Summary: Python implementation of the Swarm Ionospheric Polar Electrodynamics (Swipe) model
Author: Karl M. Laundal
Author-email: "Spencer M. Hatch" <spencer.hatch@ift.uib.no>
Maintainer-email: "Spencer M. Hatch" <spencer.hatch@ift.uib.no>
License: MIT License
Project-URL: homepage, https://earth.esa.int/eogateway/activities/swipe
Project-URL: repository, https://github.com/Dartspacephysiker/pyswipe
Classifier: License :: OSI Approved :: MIT License
Classifier: Topic :: Scientific/Engineering :: Physics
Classifier: Intended Audience :: Science/Research
Classifier: Operating System :: OS Independent
Classifier: License :: OSI Approved :: MIT License
Classifier: Programming Language :: Python
Classifier: Programming Language :: Python :: 3
Classifier: Development Status :: 4 - Beta
Requires-Python: >=3.7
License-File: LICENSE
Requires-Dist: numpy>=1.14
Requires-Dist: future>=0.16
Requires-Dist: matplotlib
Requires-Dist: scipy>=0.9
Requires-Dist: toolz>=0.8
Requires-Dist: pandas>=0.20
Requires-Dist: dask
Requires-Dist: apexpy>=1.0
Requires-Dist: ppigrf>=1.0
Requires-Dist: pyamps>=1.4.0
Provides-Extra: test
Requires-Dist: pytest>=6; extra == "test"
Provides-Extra: dev
Requires-Dist: pytest>=6; extra == "dev"
Requires-Dist: Sphinx; extra == "dev"
Dynamic: license-file
